{
  "id": "en-US:2026-06-30:0f87e5bbe9a42af9639433e88687fd43",
  "region": "en-US",
  "date": "2026-06-30",
  "title": "Where shadows stretch tall",
  "copyright": "Giraffes at sunset in the Masai Mara National Reserve, Kenya (© danm/Getty Images)",
  "copyrightLink": "https://www.bing.com/search?q=Masai+Mara+National+Reserve&form=hpcapt&filters=HpDate%3a%2220260630_0700%22",
  "imageUrl": "https://www.bing.com/th?id=OHR.MasaiGiraffe_EN-US2240704874_UHD.jpg&rf=LaDigue_UHD.jpg&pid=hp&w=3840&h=2160&rs=1&c=4",
  "downloadUrl": "https://www.bing.com/th?id=OHR.MasaiGiraffe_EN-US2240704874_UHD.jpg&pid=hp&w=3840&h=2160&rs=1&c=4",
  "thumbnailUrl": "https://www.bing.com/th?id=OHR.MasaiGiraffe_EN-US2240704874_UHD.jpg&pid=hp&w=384&h=216&rs=1&c=4",
  "sourceUrl": "https://www.bing.com/search?q=Where%20shadows%20stretch%20tall",
  "createdAt": "2026-06-30T18:10:42.193Z",
  "updatedAt": "2026-06-30T18:10:42.193Z"
}
