{
  "id": "de-DE:2026-05-28:99b7b66542eb10ba058c3d557abd8872",
  "region": "de-DE",
  "date": "2026-05-28",
  "title": "Ein Gipfelmoment der Geschichte",
  "copyright": "Gipfel des Mount Everest, Sagarmatha-Nationalpark, Nepal (© fotoVoyager/Getty Images)",
  "copyrightLink": "https://www.bing.com/search?q=Mt+Everest+Erstbesteigung+1953&form=hpcapt&filters=HpDate%3a%2220260528_2200%22",
  "imageUrl": "https://www.bing.com/th?id=OHR.SummitEverest_DE-DE3618626129_UHD.jpg&rf=LaDigue_UHD.jpg&pid=hp&w=3840&h=2160&rs=1&c=4",
  "downloadUrl": "https://www.bing.com/th?id=OHR.SummitEverest_DE-DE3618626129_UHD.jpg&pid=hp&w=3840&h=2160&rs=1&c=4",
  "thumbnailUrl": "https://www.bing.com/th?id=OHR.SummitEverest_DE-DE3618626129_UHD.jpg&pid=hp&w=384&h=216&rs=1&c=4",
  "sourceUrl": "https://www.bing.com/search?q=Ein%20Gipfelmoment%20der%20Geschichte",
  "createdAt": "2026-05-29T07:08:54.782Z",
  "updatedAt": "2026-05-29T07:08:54.782Z"
}
